exampletutorial/__init__.py
exampletutorial/synthesize.py
exampletutorial-0.0.1.dist-info/LICENSE
exampletutorial-0.0.1.dist-info/METADATA
exampletutorial-0.0.1.dist-info/WHEEL
exampletutorial-0.0.1.dist-info/top_level.txt
exampletutorial-0.0.1.dist-info/RECORD
